rollnumber_package/__init__.py
rollnumber_package/display.py
rollnumber_package-0.1.dist-info/METADATA
rollnumber_package-0.1.dist-info/WHEEL
rollnumber_package-0.1.dist-info/top_level.txt
rollnumber_package-0.1.dist-info/RECORD
